echofilter/__init__.py
echofilter/__main__.py
echofilter/__meta__.py
echofilter/checkpoints.yaml
echofilter/ev2csv.py
echofilter/generate_shards.py
echofilter/inference.py
echofilter/path.py
echofilter/plotting.py
echofilter/train.py
echofilter/utils.py
echofilter/data/__init__.py
echofilter/data/dataset.py
echofilter/data/transforms.py
echofilter/data/utils.py
echofilter/nn/__init__.py
echofilter/nn/unet.py
echofilter/nn/utils.py
echofilter/nn/wrapper.py
echofilter/nn/modules/__init__.py
echofilter/nn/modules/activations.py
echofilter/nn/modules/blocks.py
echofilter/nn/modules/conv.py
echofilter/nn/modules/pathing.py
echofilter/nn/modules/utils.py
echofilter/optim/__init__.py
echofilter/optim/criterions.py
echofilter/optim/meters.py
echofilter/optim/schedulers.py
echofilter/optim/torch_backports.py
echofilter/optim/utils.py
echofilter/raw/__init__.py
echofilter/raw/loader.py
echofilter/raw/manipulate.py
echofilter/raw/metadata.py
echofilter/raw/shardloader.py
echofilter/raw/utils.py
echofilter/ui/__init__.py
echofilter/ui/checkpoints.py
echofilter/ui/formatters.py
echofilter/ui/inference_cli.py
echofilter/ui/style.py
echofilter/ui/train_cli.py
echofilter/win/__init__.py
echofilter/win/ev.py
echofilter/win/manager.py
echofilter-1.2.0.dist-info/COPYING
echofilter-1.2.0.dist-info/METADATA
echofilter-1.2.0.dist-info/WHEEL
echofilter-1.2.0.dist-info/entry_points.txt
echofilter-1.2.0.dist-info/top_level.txt
echofilter-1.2.0.dist-info/RECORD
