Metadata-Version: 2.1
Name: echofilter
Version: 1.2.0
Summary: Remove echosounder noise by identifying the ocean floor and entrained air at the ocean surface.
Home-page: https://github.com/DeepSenseCA/echofilter
Author: Scott C. Lowe
Author-email: scott.code.lowe@gmail.com
License: AGPLv3
Project-URL: Documentation, https://echofilter.readthedocs.io
Project-URL: Source Code, https://github.com/DeepSenseCA/echofilter
Project-URL: Bug Tracker, https://github.com/DeepSenseCA/echofilter/issues
Project-URL: Citation, https://www.doi.org/10.3389/fmars.2022.867857
Classifier: Development Status :: 5 - Production/Stable
Classifier: Intended Audience :: Science/Research
Classifier: License :: OSI Approved :: GNU Affero General Public License v3
Classifier: Natural Language :: English
Classifier: Programming Language :: Python
Classifier: Programming Language :: Python :: 3
Classifier: Programming Language :: Python :: 3.6
Classifier: Programming Language :: Python :: 3.7
Classifier: Programming Language :: Python :: 3.8
Classifier: Programming Language :: Python :: 3.9
Classifier: Programming Language :: Python :: 3.10
Classifier: Topic :: Scientific/Engineering
Classifier: Topic :: Scientific/Engineering :: Bio-Informatics
Classifier: Topic :: Scientific/Engineering :: Hydrology
Classifier: Topic :: Scientific/Engineering :: Image Processing
Classifier: Topic :: Scientific/Engineering :: Image Recognition
Requires-Python: >=3.6,<3.11
License-File: COPYING
Requires-Dist: appdirs
Requires-Dist: colorama
Requires-Dist: configargparse
Requires-Dist: matplotlib
Requires-Dist: numpy
Requires-Dist: pandas
Requires-Dist: pyyaml
Requires-Dist: requests
Requires-Dist: scikit-image
Requires-Dist: scipy
Requires-Dist: torch (<1.12.0)
Requires-Dist: torchvision (<0.13.0)
Requires-Dist: tqdm
Requires-Dist: pywin32 ; platform_system == "Windows"
Provides-Extra: all
Requires-Dist: apex ; extra == 'all'
Requires-Dist: black (==22.10.0) ; extra == 'all'
Requires-Dist: identify (>=1.4.20) ; extra == 'all'
Requires-Dist: jupyter[notebook] ; extra == 'all'
Requires-Dist: matplotlib ; extra == 'all'
Requires-Dist: myst-parser ; extra == 'all'
Requires-Dist: parametrize ; extra == 'all'
Requires-Dist: pre-commit ; extra == 'all'
Requires-Dist: pyinstaller ; extra == 'all'
Requires-Dist: pypandoc (>=1.6.3) ; extra == 'all'
Requires-Dist: pytest-cov ; extra == 'all'
Requires-Dist: pytest (>=3.5.0) ; extra == 'all'
Requires-Dist: seaborn ; extra == 'all'
Requires-Dist: sphinx-argparse ; extra == 'all'
Requires-Dist: sphinx-autobuild ; extra == 'all'
Requires-Dist: sphinx (<5,>=3.5.4) ; extra == 'all'
Requires-Dist: sphinx-book-theme ; extra == 'all'
Requires-Dist: tensorboard ; extra == 'all'
Requires-Dist: torch-lr-finder (>=0.2.0) ; extra == 'all'
Requires-Dist: tqdm ; extra == 'all'
Provides-Extra: dev
Requires-Dist: black (==22.10.0) ; extra == 'dev'
Requires-Dist: identify (>=1.4.20) ; extra == 'dev'
Requires-Dist: pre-commit ; extra == 'dev'
Requires-Dist: pyinstaller ; extra == 'dev'
Provides-Extra: docs
Requires-Dist: myst-parser ; extra == 'docs'
Requires-Dist: pypandoc (>=1.6.3) ; extra == 'docs'
Requires-Dist: sphinx (<5,>=3.5.4) ; extra == 'docs'
Requires-Dist: sphinx-argparse ; extra == 'docs'
Requires-Dist: sphinx-autobuild ; extra == 'docs'
Requires-Dist: sphinx-book-theme ; extra == 'docs'
Provides-Extra: plots
Requires-Dist: jupyter[notebook] ; extra == 'plots'
Requires-Dist: matplotlib ; extra == 'plots'
Requires-Dist: seaborn ; extra == 'plots'
Requires-Dist: tqdm ; extra == 'plots'
Provides-Extra: test
Requires-Dist: parametrize ; extra == 'test'
Requires-Dist: pytest (>=3.5.0) ; extra == 'test'
Requires-Dist: pytest-cov ; extra == 'test'
Provides-Extra: train
Requires-Dist: apex ; extra == 'train'
Requires-Dist: seaborn ; extra == 'train'
Requires-Dist: tensorboard ; extra == 'train'
Requires-Dist: torch-lr-finder (>=0.2.0) ; extra == 'train'
